skollama/__init__.py
skollama/classification/__init__.py
skollama/llm/ollama/completion.py
skollama/llm/ollama/embedding.py
skollama/llm/ollama/mixin.py
skollama/llm/ollama/clients/ollama/completion.py
skollama/llm/ollama/clients/ollama/credentials.py
skollama/llm/ollama/clients/ollama/embedding.py
skollama/models/ollama/vectorization.py
skollama/models/ollama/classification/few_shot.py
skollama/models/ollama/classification/zero_shot.py
skollama/models/ollama/tagging/ner.py
skollama/models/ollama/text2text/summarization.py
skollama/models/ollama/text2text/translation.py
skollama/text2text/__init__.py
skollama/vectorization/__init__.py
scikit_ollama-0.3.2.dist-info/METADATA
scikit_ollama-0.3.2.dist-info/WHEEL
scikit_ollama-0.3.2.dist-info/top_level.txt
scikit_ollama-0.3.2.dist-info/RECORD
