Metadata-Version: 2.2
Name: scikit-ollama
Version: 0.3.2
Summary: Scikit-Ollama: an extension of Scikit-LLM for Ollama served models.
Author-email: Andreas Karasenko <andreas.karasenko@googlemail.com>
License: MIT
Classifier: Programming Language :: Python :: 3
Classifier: License :: OSI Approved :: MIT License
Classifier: Operating System :: OS Independent
Requires-Python: >=3.9
Requires-Dist: scikit-llm>=1.3.0
Requires-Dist: ollama>=0.4.7
Requires-Dist: openai>=1.59.9
Requires-Dist: pydantic
